wilk/__init__.py
foyou_wilk-1.1.12.dist-info/LICENSE
foyou_wilk-1.1.12.dist-info/METADATA
foyou_wilk-1.1.12.dist-info/WHEEL
foyou_wilk-1.1.12.dist-info/entry_points.txt
foyou_wilk-1.1.12.dist-info/top_level.txt
foyou_wilk-1.1.12.dist-info/RECORD
