Metadata-Version: 2.2
Name: foyou-wilk
Version: 1.1.12
Summary: python pypi package https://github.com/foyoux/weixin-wxposed-silk-voice
Home-page: https://github.com/foyoux/weixin-wxposed-silk-voice
Author: foyou
Author-email: yimi.0822@qq.com
License: GPL-3.0
Project-URL: Source, https://github.com/foyoux/weixin-wxposed-silk-voice
Project-URL: Bug Tracker, https://github.com/foyoux/weixin-wxposed-silk-voice/issues
Keywords: wechat weixin xpsoed silk voice
Classifier: Programming Language :: Python :: 3
Classifier: Programming Language :: Python :: 3.7
Classifier: Programming Language :: Python :: 3.8
Classifier: Programming Language :: Python :: 3.9
Classifier: Programming Language :: Python :: 3.10
Classifier: Programming Language :: Python :: 3.11
Classifier: License :: OSI Approved :: GNU General Public License v3 (GPLv3)
Classifier: Environment :: Console
Classifier: Natural Language :: Chinese (Simplified)
Classifier: Development Status :: 4 - Beta
Requires-Python: >=3.7
License-File: LICENSE
Requires-Dist: av
Requires-Dist: pilk
